unboil_fastapi_stripe/__init__.py
unboil_fastapi_stripe/config.py
unboil_fastapi_stripe/events.py
unboil_fastapi_stripe/routes.py
unboil_fastapi_stripe-0.1.19.dist-info/METADATA
unboil_fastapi_stripe-0.1.19.dist-info/WHEEL
unboil_fastapi_stripe-0.1.19.dist-info/RECORD
