Metadata-Version: 2.4
Name: unboil-fastapi-stripe
Version: 0.1.19
Summary: Add your description here
Author: eyueldk
Requires-Dist: fastapi>=0.100.0
Requires-Dist: httpx>=0.20.0
Requires-Dist: pydantic-settings>=2.0.0
Requires-Dist: pydantic>=2.0.0
Requires-Dist: sqlalchemy>=2.0.0
Requires-Dist: stripe>=12.0.0
Requires-Dist: unboil-utils-fastapi
Requires-Dist: unboil-utils-sqlalchemy
